{
  "dispatched_alerts": [
    {
      "attempt": 1,
      "channel": "telegram",
      "event_id": "ff-calendar-148364",
      "kind": "precheck",
      "scheduled_for": "2026-07-14T13:13:00-06:00",
      "sent_at": "2026-07-14T15:00:28.424295-06:00"
    },
    {
      "attempt": 1,
      "channel": "telegram",
      "event_id": "ff-calendar-153054",
      "kind": "precheck",
      "scheduled_for": "2026-07-14T13:13:00-06:00",
      "sent_at": "2026-07-14T15:00:28.424295-06:00"
    },
    {
      "attempt": 1,
      "channel": "telegram",
      "event_id": "ff-calendar-148333",
      "kind": "precheck",
      "scheduled_for": "2026-07-14T13:13:00-06:00",
      "sent_at": "2026-07-14T15:00:28.424295-06:00"
    },
    {
      "attempt": 1,
      "channel": "telegram",
      "event_id": "ff-calendar-148349",
      "kind": "precheck",
      "scheduled_for": "2026-07-14T13:13:00-06:00",
      "sent_at": "2026-07-14T15:00:28.424295-06:00"
    },
    {
      "attempt": 1,
      "channel": "telegram",
      "event_id": "ff-calendar-153330",
      "kind": "precheck",
      "scheduled_for": "2026-07-14T14:43:00-06:00",
      "sent_at": "2026-07-14T15:00:28.424295-06:00"
    },
    {
      "attempt": 1,
      "channel": "telegram",
      "event_id": "ff-calendar-148364",
      "kind": "result",
      "scheduled_for": "2026-07-14T13:31:00-06:00",
      "sent_at": "2026-07-14T15:00:28.424295-06:00"
    },
    {
      "attempt": 2,
      "channel": "telegram",
      "event_id": "ff-calendar-148364",
      "kind": "result",
      "scheduled_for": "2026-07-14T13:33:00-06:00",
      "sent_at": "2026-07-14T15:00:28.424295-06:00"
    },
    {
      "attempt": 3,
      "channel": "telegram",
      "event_id": "ff-calendar-148364",
      "kind": "result",
      "scheduled_for": "2026-07-14T13:35:00-06:00",
      "sent_at": "2026-07-14T15:00:28.424295-06:00"
    },
    {
      "attempt": 1,
      "channel": "telegram",
      "event_id": "ff-calendar-153054",
      "kind": "result",
      "scheduled_for": "2026-07-14T13:31:00-06:00",
      "sent_at": "2026-07-14T15:00:28.424295-06:00"
    },
    {
      "attempt": 2,
      "channel": "telegram",
      "event_id": "ff-calendar-153054",
      "kind": "result",
      "scheduled_for": "2026-07-14T13:33:00-06:00",
      "sent_at": "2026-07-14T15:00:28.424295-06:00"
    },
    {
      "attempt": 3,
      "channel": "telegram",
      "event_id": "ff-calendar-153054",
      "kind": "result",
      "scheduled_for": "2026-07-14T13:35:00-06:00",
      "sent_at": "2026-07-14T15:00:28.424295-06:00"
    },
    {
      "attempt": 1,
      "channel": "telegram",
      "event_id": "ff-calendar-148333",
      "kind": "result",
      "scheduled_for": "2026-07-14T13:31:00-06:00",
      "sent_at": "2026-07-14T15:00:28.424295-06:00"
    },
    {
      "attempt": 2,
      "channel": "telegram",
      "event_id": "ff-calendar-148333",
      "kind": "result",
      "scheduled_for": "2026-07-14T13:33:00-06:00",
      "sent_at": "2026-07-14T15:00:28.424295-06:00"
    },
    {
      "attempt": 3,
      "channel": "telegram",
      "event_id": "ff-calendar-148333",
      "kind": "result",
      "scheduled_for": "2026-07-14T13:35:00-06:00",
      "sent_at": "2026-07-14T15:00:28.424295-06:00"
    },
    {
      "attempt": 1,
      "channel": "telegram",
      "event_id": "ff-calendar-148349",
      "kind": "result",
      "scheduled_for": "2026-07-14T13:31:00-06:00",
      "sent_at": "2026-07-14T15:00:28.424295-06:00"
    },
    {
      "attempt": 2,
      "channel": "telegram",
      "event_id": "ff-calendar-148349",
      "kind": "result",
      "scheduled_for": "2026-07-14T13:33:00-06:00",
      "sent_at": "2026-07-14T15:00:28.424295-06:00"
    },
    {
      "attempt": 3,
      "channel": "telegram",
      "event_id": "ff-calendar-148349",
      "kind": "result",
      "scheduled_for": "2026-07-14T13:35:00-06:00",
      "sent_at": "2026-07-14T15:00:28.424295-06:00"
    },
    {
      "attempt": 1,
      "channel": "telegram",
      "event_id": "ff-calendar-153330",
      "kind": "precheck",
      "scheduled_for": "2026-07-14T09:43:00-06:00",
      "sent_at": "2026-07-14T16:06:41.091381-06:00"
    },
    {
      "attempt": 1,
      "channel": "telegram",
      "event_id": "ff-calendar-153384",
      "kind": "precheck",
      "scheduled_for": "2026-07-14T15:43:00-06:00",
      "sent_at": "2026-07-14T16:06:41.091381-06:00"
    },
    {
      "attempt": 1,
      "channel": "telegram",
      "event_id": "ff-calendar-148401",
      "kind": "precheck",
      "scheduled_for": "2026-07-15T08:13:00-06:00",
      "sent_at": "2026-07-15T08:28:49.171235-06:00"
    },
    {
      "attempt": 1,
      "channel": "telegram",
      "event_id": "ff-calendar-148384",
      "kind": "precheck",
      "scheduled_for": "2026-07-15T08:13:00-06:00",
      "sent_at": "2026-07-15T08:28:49.171235-06:00"
    },
    {
      "attempt": 1,
      "channel": "telegram",
      "event_id": "ff-calendar-148401",
      "kind": "precheck",
      "scheduled_for": "2026-07-15T05:13:00-06:00",
      "sent_at": "2026-07-15T10:04:39.109851-06:00"
    },
    {
      "attempt": 1,
      "channel": "telegram",
      "event_id": "ff-calendar-148384",
      "kind": "precheck",
      "scheduled_for": "2026-07-15T05:13:00-06:00",
      "sent_at": "2026-07-15T10:04:39.109851-06:00"
    },
    {
      "attempt": 1,
      "channel": "telegram",
      "event_id": "ff-calendar-146549",
      "kind": "precheck",
      "scheduled_for": "2026-07-15T06:28:00-06:00",
      "sent_at": "2026-07-15T10:04:39.109851-06:00"
    },
    {
      "attempt": 1,
      "channel": "telegram",
      "event_id": "ff-calendar-146543",
      "kind": "precheck",
      "scheduled_for": "2026-07-15T06:28:00-06:00",
      "sent_at": "2026-07-15T10:04:39.109851-06:00"
    },
    {
      "attempt": 1,
      "channel": "telegram",
      "event_id": "ff-calendar-146535",
      "kind": "precheck",
      "scheduled_for": "2026-07-15T06:28:00-06:00",
      "sent_at": "2026-07-15T10:04:39.109851-06:00"
    },
    {
      "attempt": 1,
      "channel": "telegram",
      "event_id": "ff-calendar-153380",
      "kind": "precheck",
      "scheduled_for": "2026-07-15T06:43:00-06:00",
      "sent_at": "2026-07-15T10:04:39.109851-06:00"
    },
    {
      "attempt": 1,
      "channel": "telegram",
      "event_id": "ff-calendar-146555",
      "kind": "precheck",
      "scheduled_for": "2026-07-15T07:28:00-06:00",
      "sent_at": "2026-07-15T10:04:39.109851-06:00"
    },
    {
      "attempt": 1,
      "channel": "telegram",
      "event_id": "ff-calendar-148401",
      "kind": "result",
      "scheduled_for": "2026-07-15T05:31:00-06:00",
      "sent_at": "2026-07-15T10:04:39.109851-06:00"
    },
    {
      "attempt": 2,
      "channel": "telegram",
      "event_id": "ff-calendar-148401",
      "kind": "result",
      "scheduled_for": "2026-07-15T05:33:00-06:00",
      "sent_at": "2026-07-15T10:04:39.109851-06:00"
    },
    {
      "attempt": 3,
      "channel": "telegram",
      "event_id": "ff-calendar-148401",
      "kind": "result",
      "scheduled_for": "2026-07-15T05:35:00-06:00",
      "sent_at": "2026-07-15T10:04:39.109851-06:00"
    },
    {
      "attempt": 1,
      "channel": "telegram",
      "event_id": "ff-calendar-148384",
      "kind": "result",
      "scheduled_for": "2026-07-15T05:31:00-06:00",
      "sent_at": "2026-07-15T10:04:39.109851-06:00"
    },
    {
      "attempt": 2,
      "channel": "telegram",
      "event_id": "ff-calendar-148384",
      "kind": "result",
      "scheduled_for": "2026-07-15T05:33:00-06:00",
      "sent_at": "2026-07-15T10:04:39.109851-06:00"
    },
    {
      "attempt": 3,
      "channel": "telegram",
      "event_id": "ff-calendar-148384",
      "kind": "result",
      "scheduled_for": "2026-07-15T05:35:00-06:00",
      "sent_at": "2026-07-15T10:04:39.109851-06:00"
    },
    {
      "attempt": 1,
      "channel": "telegram",
      "event_id": "ff-calendar-146535",
      "kind": "result",
      "scheduled_for": "2026-07-15T06:46:00-06:00",
      "sent_at": "2026-07-15T10:04:39.109851-06:00"
    },
    {
      "attempt": 2,
      "channel": "telegram",
      "event_id": "ff-calendar-146535",
      "kind": "result",
      "scheduled_for": "2026-07-15T06:48:00-06:00",
      "sent_at": "2026-07-15T10:04:39.109851-06:00"
    },
    {
      "attempt": 3,
      "channel": "telegram",
      "event_id": "ff-calendar-146535",
      "kind": "result",
      "scheduled_for": "2026-07-15T06:50:00-06:00",
      "sent_at": "2026-07-15T10:04:39.109851-06:00"
    },
    {
      "attempt": 1,
      "channel": "telegram",
      "event_id": "ff-calendar-146549",
      "kind": "precheck",
      "scheduled_for": "2026-07-15T09:28:00-06:00",
      "sent_at": "2026-07-15T11:34:45.761092-06:00"
    },
    {
      "attempt": 1,
      "channel": "telegram",
      "event_id": "ff-calendar-146543",
      "kind": "precheck",
      "scheduled_for": "2026-07-15T09:28:00-06:00",
      "sent_at": "2026-07-15T11:34:45.761092-06:00"
    },
    {
      "attempt": 1,
      "channel": "telegram",
      "event_id": "ff-calendar-146535",
      "kind": "precheck",
      "scheduled_for": "2026-07-15T09:28:00-06:00",
      "sent_at": "2026-07-15T11:34:45.761092-06:00"
    },
    {
      "attempt": 1,
      "channel": "telegram",
      "event_id": "ff-calendar-153380",
      "kind": "precheck",
      "scheduled_for": "2026-07-15T09:43:00-06:00",
      "sent_at": "2026-07-15T11:34:45.761092-06:00"
    },
    {
      "attempt": 1,
      "channel": "telegram",
      "event_id": "ff-calendar-146555",
      "kind": "precheck",
      "scheduled_for": "2026-07-15T10:28:00-06:00",
      "sent_at": "2026-07-15T11:34:45.761092-06:00"
    },
    {
      "attempt": 1,
      "channel": "telegram",
      "event_id": "ff-calendar-148401",
      "kind": "result",
      "scheduled_for": "2026-07-15T08:31:00-06:00",
      "sent_at": "2026-07-15T11:34:45.761092-06:00"
    },
    {
      "attempt": 2,
      "channel": "telegram",
      "event_id": "ff-calendar-148401",
      "kind": "result",
      "scheduled_for": "2026-07-15T08:33:00-06:00",
      "sent_at": "2026-07-15T11:34:45.761092-06:00"
    },
    {
      "attempt": 3,
      "channel": "telegram",
      "event_id": "ff-calendar-148401",
      "kind": "result",
      "scheduled_for": "2026-07-15T08:35:00-06:00",
      "sent_at": "2026-07-15T11:34:45.761092-06:00"
    },
    {
      "attempt": 1,
      "channel": "telegram",
      "event_id": "ff-calendar-148384",
      "kind": "result",
      "scheduled_for": "2026-07-15T08:31:00-06:00",
      "sent_at": "2026-07-15T11:34:45.761092-06:00"
    },
    {
      "attempt": 2,
      "channel": "telegram",
      "event_id": "ff-calendar-148384",
      "kind": "result",
      "scheduled_for": "2026-07-15T08:33:00-06:00",
      "sent_at": "2026-07-15T11:34:45.761092-06:00"
    },
    {
      "attempt": 3,
      "channel": "telegram",
      "event_id": "ff-calendar-148384",
      "kind": "result",
      "scheduled_for": "2026-07-15T08:35:00-06:00",
      "sent_at": "2026-07-15T11:34:45.761092-06:00"
    },
    {
      "attempt": 1,
      "channel": "telegram",
      "event_id": "ff-calendar-146535",
      "kind": "result",
      "scheduled_for": "2026-07-15T09:46:00-06:00",
      "sent_at": "2026-07-15T11:34:45.761092-06:00"
    },
    {
      "attempt": 2,
      "channel": "telegram",
      "event_id": "ff-calendar-146535",
      "kind": "result",
      "scheduled_for": "2026-07-15T09:48:00-06:00",
      "sent_at": "2026-07-15T11:34:45.761092-06:00"
    },
    {
      "attempt": 3,
      "channel": "telegram",
      "event_id": "ff-calendar-146535",
      "kind": "result",
      "scheduled_for": "2026-07-15T09:50:00-06:00",
      "sent_at": "2026-07-15T11:34:45.761092-06:00"
    },
    {
      "attempt": 1,
      "channel": "telegram",
      "event_id": "ff-calendar-148401",
      "kind": "precheck",
      "scheduled_for": "2026-07-15T06:13:00-06:00",
      "sent_at": "2026-07-15T12:42:17.965877-06:00"
    },
    {
      "attempt": 1,
      "channel": "telegram",
      "event_id": "ff-calendar-148384",
      "kind": "precheck",
      "scheduled_for": "2026-07-15T06:13:00-06:00",
      "sent_at": "2026-07-15T12:42:17.965877-06:00"
    },
    {
      "attempt": 1,
      "channel": "telegram",
      "event_id": "ff-calendar-146549",
      "kind": "precheck",
      "scheduled_for": "2026-07-15T07:28:00-06:00",
      "sent_at": "2026-07-15T12:42:17.965877-06:00"
    },
    {
      "attempt": 1,
      "channel": "telegram",
      "event_id": "ff-calendar-146543",
      "kind": "precheck",
      "scheduled_for": "2026-07-15T07:28:00-06:00",
      "sent_at": "2026-07-15T12:42:17.965877-06:00"
    },
    {
      "attempt": 1,
      "channel": "telegram",
      "event_id": "ff-calendar-146535",
      "kind": "precheck",
      "scheduled_for": "2026-07-15T07:28:00-06:00",
      "sent_at": "2026-07-15T12:42:17.965877-06:00"
    },
    {
      "attempt": 1,
      "channel": "telegram",
      "event_id": "ff-calendar-153380",
      "kind": "precheck",
      "scheduled_for": "2026-07-15T07:43:00-06:00",
      "sent_at": "2026-07-15T12:42:17.965877-06:00"
    },
    {
      "attempt": 1,
      "channel": "telegram",
      "event_id": "ff-calendar-146555",
      "kind": "precheck",
      "scheduled_for": "2026-07-15T08:28:00-06:00",
      "sent_at": "2026-07-15T12:42:17.965877-06:00"
    },
    {
      "attempt": 1,
      "channel": "telegram",
      "event_id": "ff-calendar-148401",
      "kind": "result",
      "scheduled_for": "2026-07-15T06:31:00-06:00",
      "sent_at": "2026-07-15T12:42:17.965877-06:00"
    },
    {
      "attempt": 2,
      "channel": "telegram",
      "event_id": "ff-calendar-148401",
      "kind": "result",
      "scheduled_for": "2026-07-15T06:33:00-06:00",
      "sent_at": "2026-07-15T12:42:17.965877-06:00"
    },
    {
      "attempt": 3,
      "channel": "telegram",
      "event_id": "ff-calendar-148401",
      "kind": "result",
      "scheduled_for": "2026-07-15T06:35:00-06:00",
      "sent_at": "2026-07-15T12:42:17.965877-06:00"
    },
    {
      "attempt": 1,
      "channel": "telegram",
      "event_id": "ff-calendar-148384",
      "kind": "result",
      "scheduled_for": "2026-07-15T06:31:00-06:00",
      "sent_at": "2026-07-15T12:42:17.965877-06:00"
    },
    {
      "attempt": 2,
      "channel": "telegram",
      "event_id": "ff-calendar-148384",
      "kind": "result",
      "scheduled_for": "2026-07-15T06:33:00-06:00",
      "sent_at": "2026-07-15T12:42:17.965877-06:00"
    },
    {
      "attempt": 3,
      "channel": "telegram",
      "event_id": "ff-calendar-148384",
      "kind": "result",
      "scheduled_for": "2026-07-15T06:35:00-06:00",
      "sent_at": "2026-07-15T12:42:17.965877-06:00"
    },
    {
      "attempt": 1,
      "channel": "telegram",
      "event_id": "ff-calendar-146535",
      "kind": "result",
      "scheduled_for": "2026-07-15T07:46:00-06:00",
      "sent_at": "2026-07-15T12:42:17.965877-06:00"
    },
    {
      "attempt": 2,
      "channel": "telegram",
      "event_id": "ff-calendar-146535",
      "kind": "result",
      "scheduled_for": "2026-07-15T07:48:00-06:00",
      "sent_at": "2026-07-15T12:42:17.965877-06:00"
    },
    {
      "attempt": 3,
      "channel": "telegram",
      "event_id": "ff-calendar-146535",
      "kind": "result",
      "scheduled_for": "2026-07-15T07:50:00-06:00",
      "sent_at": "2026-07-15T12:42:17.965877-06:00"
    },
    {
      "attempt": 1,
      "channel": "telegram",
      "event_id": "ff-calendar-148401",
      "kind": "precheck",
      "scheduled_for": "2026-07-15T07:13:00-06:00",
      "sent_at": "2026-07-15T14:47:38.878578-06:00"
    },
    {
      "attempt": 1,
      "channel": "telegram",
      "event_id": "ff-calendar-148384",
      "kind": "precheck",
      "scheduled_for": "2026-07-15T07:13:00-06:00",
      "sent_at": "2026-07-15T14:47:38.878578-06:00"
    },
    {
      "attempt": 1,
      "channel": "telegram",
      "event_id": "ff-calendar-146549",
      "kind": "precheck",
      "scheduled_for": "2026-07-15T08:28:00-06:00",
      "sent_at": "2026-07-15T14:47:38.878578-06:00"
    },
    {
      "attempt": 1,
      "channel": "telegram",
      "event_id": "ff-calendar-146543",
      "kind": "precheck",
      "scheduled_for": "2026-07-15T08:28:00-06:00",
      "sent_at": "2026-07-15T14:47:38.878578-06:00"
    },
    {
      "attempt": 1,
      "channel": "telegram",
      "event_id": "ff-calendar-146535",
      "kind": "precheck",
      "scheduled_for": "2026-07-15T08:28:00-06:00",
      "sent_at": "2026-07-15T14:47:38.878578-06:00"
    },
    {
      "attempt": 1,
      "channel": "telegram",
      "event_id": "ff-calendar-153380",
      "kind": "precheck",
      "scheduled_for": "2026-07-15T08:43:00-06:00",
      "sent_at": "2026-07-15T14:47:38.878578-06:00"
    },
    {
      "attempt": 1,
      "channel": "telegram",
      "event_id": "ff-calendar-146555",
      "kind": "precheck",
      "scheduled_for": "2026-07-15T09:28:00-06:00",
      "sent_at": "2026-07-15T14:47:38.878578-06:00"
    },
    {
      "attempt": 1,
      "channel": "telegram",
      "event_id": "ff-calendar-148401",
      "kind": "result",
      "scheduled_for": "2026-07-15T07:31:00-06:00",
      "sent_at": "2026-07-15T14:47:38.878578-06:00"
    },
    {
      "attempt": 2,
      "channel": "telegram",
      "event_id": "ff-calendar-148401",
      "kind": "result",
      "scheduled_for": "2026-07-15T07:33:00-06:00",
      "sent_at": "2026-07-15T14:47:38.878578-06:00"
    },
    {
      "attempt": 3,
      "channel": "telegram",
      "event_id": "ff-calendar-148401",
      "kind": "result",
      "scheduled_for": "2026-07-15T07:35:00-06:00",
      "sent_at": "2026-07-15T14:47:38.878578-06:00"
    },
    {
      "attempt": 1,
      "channel": "telegram",
      "event_id": "ff-calendar-148384",
      "kind": "result",
      "scheduled_for": "2026-07-15T07:31:00-06:00",
      "sent_at": "2026-07-15T14:47:38.878578-06:00"
    },
    {
      "attempt": 2,
      "channel": "telegram",
      "event_id": "ff-calendar-148384",
      "kind": "result",
      "scheduled_for": "2026-07-15T07:33:00-06:00",
      "sent_at": "2026-07-15T14:47:38.878578-06:00"
    },
    {
      "attempt": 3,
      "channel": "telegram",
      "event_id": "ff-calendar-148384",
      "kind": "result",
      "scheduled_for": "2026-07-15T07:35:00-06:00",
      "sent_at": "2026-07-15T14:47:38.878578-06:00"
    },
    {
      "attempt": 1,
      "channel": "telegram",
      "event_id": "ff-calendar-146535",
      "kind": "result",
      "scheduled_for": "2026-07-15T08:46:00-06:00",
      "sent_at": "2026-07-15T14:47:38.878578-06:00"
    },
    {
      "attempt": 2,
      "channel": "telegram",
      "event_id": "ff-calendar-146535",
      "kind": "result",
      "scheduled_for": "2026-07-15T08:48:00-06:00",
      "sent_at": "2026-07-15T14:47:38.878578-06:00"
    },
    {
      "attempt": 3,
      "channel": "telegram",
      "event_id": "ff-calendar-146535",
      "kind": "result",
      "scheduled_for": "2026-07-15T08:50:00-06:00",
      "sent_at": "2026-07-15T14:47:38.878578-06:00"
    },
    {
      "attempt": 1,
      "channel": "telegram",
      "event_id": "ff-calendar-151546",
      "kind": "precheck",
      "scheduled_for": "2026-07-16T01:43:00-06:00",
      "sent_at": "2026-07-16T03:01:08.572345-06:00"
    },
    {
      "attempt": 1,
      "channel": "telegram",
      "event_id": "ff-calendar-151546",
      "kind": "result",
      "scheduled_for": "2026-07-16T02:01:00-06:00",
      "sent_at": "2026-07-16T03:01:08.572345-06:00"
    },
    {
      "attempt": 2,
      "channel": "telegram",
      "event_id": "ff-calendar-151546",
      "kind": "result",
      "scheduled_for": "2026-07-16T02:03:00-06:00",
      "sent_at": "2026-07-16T03:01:08.572345-06:00"
    },
    {
      "attempt": 3,
      "channel": "telegram",
      "event_id": "ff-calendar-151546",
      "kind": "result",
      "scheduled_for": "2026-07-16T02:05:00-06:00",
      "sent_at": "2026-07-16T03:01:08.572345-06:00"
    },
    {
      "attempt": 1,
      "channel": "telegram",
      "event_id": "ff-calendar-151546",
      "kind": "precheck",
      "scheduled_for": "2026-07-16T00:43:00-06:00",
      "sent_at": "2026-07-16T08:48:26.595760-06:00"
    },
    {
      "attempt": 1,
      "channel": "telegram",
      "event_id": "ff-calendar-151546",
      "kind": "result",
      "scheduled_for": "2026-07-16T01:01:00-06:00",
      "sent_at": "2026-07-16T08:48:26.595760-06:00"
    },
    {
      "attempt": 2,
      "channel": "telegram",
      "event_id": "ff-calendar-151546",
      "kind": "result",
      "scheduled_for": "2026-07-16T01:03:00-06:00",
      "sent_at": "2026-07-16T08:48:26.595760-06:00"
    },
    {
      "attempt": 3,
      "channel": "telegram",
      "event_id": "ff-calendar-151546",
      "kind": "result",
      "scheduled_for": "2026-07-16T01:05:00-06:00",
      "sent_at": "2026-07-16T08:48:26.595760-06:00"
    },
    {
      "attempt": 1,
      "channel": "telegram",
      "event_id": "daily-summary-2026-07-19",
      "kind": "daily_summary",
      "scheduled_for": "2026-07-19T00:00:00-06:00",
      "sent_at": "2026-07-19T00:16:12.419071-06:00"
    },
    {
      "attempt": 1,
      "channel": "telegram",
      "event_id": "ff-calendar-149155",
      "kind": "precheck",
      "scheduled_for": "2026-07-20T05:13:00-06:00",
      "sent_at": "2026-07-20T06:30:31.779181-06:00"
    },
    {
      "attempt": 1,
      "channel": "telegram",
      "event_id": "ff-calendar-149156",
      "kind": "precheck",
      "scheduled_for": "2026-07-20T05:13:00-06:00",
      "sent_at": "2026-07-20T06:30:31.779181-06:00"
    },
    {
      "attempt": 1,
      "channel": "telegram",
      "event_id": "ff-calendar-149157",
      "kind": "precheck",
      "scheduled_for": "2026-07-20T05:13:00-06:00",
      "sent_at": "2026-07-20T06:30:31.779181-06:00"
    },
    {
      "attempt": 1,
      "channel": "telegram",
      "event_id": "ff-calendar-149155",
      "kind": "result",
      "scheduled_for": "2026-07-20T05:31:00-06:00",
      "sent_at": "2026-07-20T06:30:31.779181-06:00"
    },
    {
      "attempt": 2,
      "channel": "telegram",
      "event_id": "ff-calendar-149155",
      "kind": "result",
      "scheduled_for": "2026-07-20T05:33:00-06:00",
      "sent_at": "2026-07-20T06:30:31.779181-06:00"
    },
    {
      "attempt": 3,
      "channel": "telegram",
      "event_id": "ff-calendar-149155",
      "kind": "result",
      "scheduled_for": "2026-07-20T05:35:00-06:00",
      "sent_at": "2026-07-20T06:30:31.779181-06:00"
    },
    {
      "attempt": 1,
      "channel": "telegram",
      "event_id": "ff-calendar-149156",
      "kind": "result",
      "scheduled_for": "2026-07-20T05:31:00-06:00",
      "sent_at": "2026-07-20T06:30:31.779181-06:00"
    },
    {
      "attempt": 2,
      "channel": "telegram",
      "event_id": "ff-calendar-149156",
      "kind": "result",
      "scheduled_for": "2026-07-20T05:33:00-06:00",
      "sent_at": "2026-07-20T06:30:31.779181-06:00"
    },
    {
      "attempt": 3,
      "channel": "telegram",
      "event_id": "ff-calendar-149156",
      "kind": "result",
      "scheduled_for": "2026-07-20T05:35:00-06:00",
      "sent_at": "2026-07-20T06:30:31.779181-06:00"
    },
    {
      "attempt": 1,
      "channel": "telegram",
      "event_id": "ff-calendar-149157",
      "kind": "result",
      "scheduled_for": "2026-07-20T05:31:00-06:00",
      "sent_at": "2026-07-20T06:30:31.779181-06:00"
    },
    {
      "attempt": 2,
      "channel": "telegram",
      "event_id": "ff-calendar-149157",
      "kind": "result",
      "scheduled_for": "2026-07-20T05:33:00-06:00",
      "sent_at": "2026-07-20T06:30:31.779181-06:00"
    },
    {
      "attempt": 3,
      "channel": "telegram",
      "event_id": "ff-calendar-149157",
      "kind": "result",
      "scheduled_for": "2026-07-20T05:35:00-06:00",
      "sent_at": "2026-07-20T06:30:31.779181-06:00"
    },
    {
      "attempt": 1,
      "channel": "telegram",
      "event_id": "ff-calendar-149155",
      "kind": "precheck",
      "scheduled_for": "2026-07-20T08:13:00-06:00",
      "sent_at": "2026-07-20T08:50:16.538215-06:00"
    },
    {
      "attempt": 1,
      "channel": "telegram",
      "event_id": "ff-calendar-149156",
      "kind": "precheck",
      "scheduled_for": "2026-07-20T08:13:00-06:00",
      "sent_at": "2026-07-20T08:50:16.538215-06:00"
    },
    {
      "attempt": 1,
      "channel": "telegram",
      "event_id": "ff-calendar-149157",
      "kind": "precheck",
      "scheduled_for": "2026-07-20T08:13:00-06:00",
      "sent_at": "2026-07-20T08:50:16.538215-06:00"
    },
    {
      "attempt": 1,
      "channel": "telegram",
      "event_id": "ff-calendar-149155",
      "kind": "result",
      "scheduled_for": "2026-07-20T08:31:00-06:00",
      "sent_at": "2026-07-20T08:50:16.538215-06:00"
    },
    {
      "attempt": 2,
      "channel": "telegram",
      "event_id": "ff-calendar-149155",
      "kind": "result",
      "scheduled_for": "2026-07-20T08:33:00-06:00",
      "sent_at": "2026-07-20T08:50:16.538215-06:00"
    },
    {
      "attempt": 3,
      "channel": "telegram",
      "event_id": "ff-calendar-149155",
      "kind": "result",
      "scheduled_for": "2026-07-20T08:35:00-06:00",
      "sent_at": "2026-07-20T08:50:16.538215-06:00"
    },
    {
      "attempt": 1,
      "channel": "telegram",
      "event_id": "ff-calendar-149156",
      "kind": "result",
      "scheduled_for": "2026-07-20T08:31:00-06:00",
      "sent_at": "2026-07-20T08:50:16.538215-06:00"
    },
    {
      "attempt": 2,
      "channel": "telegram",
      "event_id": "ff-calendar-149156",
      "kind": "result",
      "scheduled_for": "2026-07-20T08:33:00-06:00",
      "sent_at": "2026-07-20T08:50:16.538215-06:00"
    },
    {
      "attempt": 3,
      "channel": "telegram",
      "event_id": "ff-calendar-149156",
      "kind": "result",
      "scheduled_for": "2026-07-20T08:35:00-06:00",
      "sent_at": "2026-07-20T08:50:16.538215-06:00"
    },
    {
      "attempt": 1,
      "channel": "telegram",
      "event_id": "ff-calendar-149157",
      "kind": "result",
      "scheduled_for": "2026-07-20T08:31:00-06:00",
      "sent_at": "2026-07-20T08:50:16.538215-06:00"
    },
    {
      "attempt": 2,
      "channel": "telegram",
      "event_id": "ff-calendar-149157",
      "kind": "result",
      "scheduled_for": "2026-07-20T08:33:00-06:00",
      "sent_at": "2026-07-20T08:50:16.538215-06:00"
    },
    {
      "attempt": 3,
      "channel": "telegram",
      "event_id": "ff-calendar-149157",
      "kind": "result",
      "scheduled_for": "2026-07-20T08:35:00-06:00",
      "sent_at": "2026-07-20T08:50:16.538215-06:00"
    },
    {
      "attempt": 1,
      "channel": "telegram",
      "event_id": "ff-calendar-149155",
      "kind": "precheck",
      "scheduled_for": "2026-07-20T07:13:00-06:00",
      "sent_at": "2026-07-20T16:26:20.206144-06:00"
    },
    {
      "attempt": 1,
      "channel": "telegram",
      "event_id": "ff-calendar-149156",
      "kind": "precheck",
      "scheduled_for": "2026-07-20T07:13:00-06:00",
      "sent_at": "2026-07-20T16:26:20.206144-06:00"
    },
    {
      "attempt": 1,
      "channel": "telegram",
      "event_id": "ff-calendar-149157",
      "kind": "precheck",
      "scheduled_for": "2026-07-20T07:13:00-06:00",
      "sent_at": "2026-07-20T16:26:20.206144-06:00"
    },
    {
      "attempt": 1,
      "channel": "telegram",
      "event_id": "ff-calendar-149155",
      "kind": "result",
      "scheduled_for": "2026-07-20T07:31:00-06:00",
      "sent_at": "2026-07-20T16:26:20.206144-06:00"
    },
    {
      "attempt": 2,
      "channel": "telegram",
      "event_id": "ff-calendar-149155",
      "kind": "result",
      "scheduled_for": "2026-07-20T07:33:00-06:00",
      "sent_at": "2026-07-20T16:26:20.206144-06:00"
    },
    {
      "attempt": 3,
      "channel": "telegram",
      "event_id": "ff-calendar-149155",
      "kind": "result",
      "scheduled_for": "2026-07-20T07:35:00-06:00",
      "sent_at": "2026-07-20T16:26:20.206144-06:00"
    },
    {
      "attempt": 1,
      "channel": "telegram",
      "event_id": "ff-calendar-149156",
      "kind": "result",
      "scheduled_for": "2026-07-20T07:31:00-06:00",
      "sent_at": "2026-07-20T16:26:20.206144-06:00"
    },
    {
      "attempt": 2,
      "channel": "telegram",
      "event_id": "ff-calendar-149156",
      "kind": "result",
      "scheduled_for": "2026-07-20T07:33:00-06:00",
      "sent_at": "2026-07-20T16:26:20.206144-06:00"
    },
    {
      "attempt": 3,
      "channel": "telegram",
      "event_id": "ff-calendar-149156",
      "kind": "result",
      "scheduled_for": "2026-07-20T07:35:00-06:00",
      "sent_at": "2026-07-20T16:26:20.206144-06:00"
    },
    {
      "attempt": 1,
      "channel": "telegram",
      "event_id": "ff-calendar-149157",
      "kind": "result",
      "scheduled_for": "2026-07-20T07:31:00-06:00",
      "sent_at": "2026-07-20T16:26:20.206144-06:00"
    },
    {
      "attempt": 2,
      "channel": "telegram",
      "event_id": "ff-calendar-149157",
      "kind": "result",
      "scheduled_for": "2026-07-20T07:33:00-06:00",
      "sent_at": "2026-07-20T16:26:20.206144-06:00"
    },
    {
      "attempt": 3,
      "channel": "telegram",
      "event_id": "ff-calendar-149157",
      "kind": "result",
      "scheduled_for": "2026-07-20T07:35:00-06:00",
      "sent_at": "2026-07-20T16:26:20.206144-06:00"
    },
    {
      "attempt": 1,
      "channel": "telegram",
      "event_id": "ff-calendar-150037",
      "kind": "precheck",
      "scheduled_for": "2026-07-20T15:28:00-06:00",
      "sent_at": "2026-07-20T17:30:45.991960-06:00"
    },
    {
      "attempt": 1,
      "channel": "telegram",
      "event_id": "ff-calendar-150037",
      "kind": "result",
      "scheduled_for": "2026-07-20T15:46:00-06:00",
      "sent_at": "2026-07-20T17:30:45.991960-06:00"
    },
    {
      "attempt": 2,
      "channel": "telegram",
      "event_id": "ff-calendar-150037",
      "kind": "result",
      "scheduled_for": "2026-07-20T15:48:00-06:00",
      "sent_at": "2026-07-20T17:30:45.991960-06:00"
    },
    {
      "attempt": 3,
      "channel": "telegram",
      "event_id": "ff-calendar-150037",
      "kind": "result",
      "scheduled_for": "2026-07-20T15:50:00-06:00",
      "sent_at": "2026-07-20T17:30:45.991960-06:00"
    },
    {
      "attempt": 1,
      "channel": "telegram",
      "event_id": "ff-calendar-149155",
      "kind": "precheck",
      "scheduled_for": "2026-07-20T13:13:00-06:00",
      "sent_at": "2026-07-20T19:01:42.614415-06:00"
    },
    {
      "attempt": 1,
      "channel": "telegram",
      "event_id": "ff-calendar-149156",
      "kind": "precheck",
      "scheduled_for": "2026-07-20T13:13:00-06:00",
      "sent_at": "2026-07-20T19:01:42.614415-06:00"
    },
    {
      "attempt": 1,
      "channel": "telegram",
      "event_id": "ff-calendar-149157",
      "kind": "precheck",
      "scheduled_for": "2026-07-20T13:13:00-06:00",
      "sent_at": "2026-07-20T19:01:42.614415-06:00"
    },
    {
      "attempt": 1,
      "channel": "telegram",
      "event_id": "ff-calendar-149155",
      "kind": "result",
      "scheduled_for": "2026-07-20T13:31:00-06:00",
      "sent_at": "2026-07-20T19:01:42.614415-06:00"
    },
    {
      "attempt": 2,
      "channel": "telegram",
      "event_id": "ff-calendar-149155",
      "kind": "result",
      "scheduled_for": "2026-07-20T13:33:00-06:00",
      "sent_at": "2026-07-20T19:01:42.614415-06:00"
    },
    {
      "attempt": 3,
      "channel": "telegram",
      "event_id": "ff-calendar-149155",
      "kind": "result",
      "scheduled_for": "2026-07-20T13:35:00-06:00",
      "sent_at": "2026-07-20T19:01:42.614415-06:00"
    },
    {
      "attempt": 1,
      "channel": "telegram",
      "event_id": "ff-calendar-149156",
      "kind": "result",
      "scheduled_for": "2026-07-20T13:31:00-06:00",
      "sent_at": "2026-07-20T19:01:42.614415-06:00"
    },
    {
      "attempt": 2,
      "channel": "telegram",
      "event_id": "ff-calendar-149156",
      "kind": "result",
      "scheduled_for": "2026-07-20T13:33:00-06:00",
      "sent_at": "2026-07-20T19:01:42.614415-06:00"
    },
    {
      "attempt": 3,
      "channel": "telegram",
      "event_id": "ff-calendar-149156",
      "kind": "result",
      "scheduled_for": "2026-07-20T13:35:00-06:00",
      "sent_at": "2026-07-20T19:01:42.614415-06:00"
    },
    {
      "attempt": 1,
      "channel": "telegram",
      "event_id": "ff-calendar-149157",
      "kind": "result",
      "scheduled_for": "2026-07-20T13:31:00-06:00",
      "sent_at": "2026-07-20T19:01:42.614415-06:00"
    },
    {
      "attempt": 2,
      "channel": "telegram",
      "event_id": "ff-calendar-149157",
      "kind": "result",
      "scheduled_for": "2026-07-20T13:33:00-06:00",
      "sent_at": "2026-07-20T19:01:42.614415-06:00"
    },
    {
      "attempt": 3,
      "channel": "telegram",
      "event_id": "ff-calendar-149157",
      "kind": "result",
      "scheduled_for": "2026-07-20T13:35:00-06:00",
      "sent_at": "2026-07-20T19:01:42.614415-06:00"
    },
    {
      "attempt": 1,
      "channel": "telegram",
      "event_id": "ff-calendar-151084",
      "kind": "precheck",
      "scheduled_for": "2026-07-21T01:43:00-06:00",
      "sent_at": "2026-07-21T03:34:38.832087-06:00"
    },
    {
      "attempt": 1,
      "channel": "telegram",
      "event_id": "ff-calendar-151084",
      "kind": "result",
      "scheduled_for": "2026-07-21T02:01:00-06:00",
      "sent_at": "2026-07-21T03:34:38.832087-06:00"
    },
    {
      "attempt": 2,
      "channel": "telegram",
      "event_id": "ff-calendar-151084",
      "kind": "result",
      "scheduled_for": "2026-07-21T02:03:00-06:00",
      "sent_at": "2026-07-21T03:34:38.832087-06:00"
    },
    {
      "attempt": 3,
      "channel": "telegram",
      "event_id": "ff-calendar-151084",
      "kind": "result",
      "scheduled_for": "2026-07-21T02:05:00-06:00",
      "sent_at": "2026-07-21T03:34:38.832087-06:00"
    },
    {
      "attempt": 1,
      "channel": "telegram",
      "event_id": "ff-calendar-151084",
      "kind": "precheck",
      "scheduled_for": "2026-07-21T00:43:00-06:00",
      "sent_at": "2026-07-21T08:55:18.164828-06:00"
    },
    {
      "attempt": 1,
      "channel": "telegram",
      "event_id": "ff-calendar-151084",
      "kind": "result",
      "scheduled_for": "2026-07-21T01:01:00-06:00",
      "sent_at": "2026-07-21T08:55:18.164828-06:00"
    },
    {
      "attempt": 2,
      "channel": "telegram",
      "event_id": "ff-calendar-151084",
      "kind": "result",
      "scheduled_for": "2026-07-21T01:03:00-06:00",
      "sent_at": "2026-07-21T08:55:18.164828-06:00"
    },
    {
      "attempt": 3,
      "channel": "telegram",
      "event_id": "ff-calendar-151084",
      "kind": "result",
      "scheduled_for": "2026-07-21T01:05:00-06:00",
      "sent_at": "2026-07-21T08:55:18.164828-06:00"
    }
  ],
  "observability": {
    "precheck": {
      "consecutive_failures": 0,
      "last_attempt_at": "2026-07-21T12:58:14.528527-06:00",
      "last_error_at": null,
      "last_error_message": null,
      "last_success_at": "2026-07-21T12:58:14.528527-06:00",
      "status": "ok"
    },
    "scraping": {
      "consecutive_failures": 0,
      "last_attempt_at": "2026-07-21T12:58:14.528527-06:00",
      "last_error_at": null,
      "last_error_message": null,
      "last_success_at": "2026-07-21T12:58:14.528527-06:00",
      "status": "ok"
    },
    "telegram": {
      "consecutive_failures": 0,
      "last_attempt_at": "2026-07-21T08:55:18.164828-06:00",
      "last_error_at": null,
      "last_error_message": null,
      "last_success_at": "2026-07-21T08:55:18.164828-06:00",
      "status": "ok"
    }
  }
}